{
    "activations": {
        "heap_overlay_pool": {
            "activation_alignment": 4,
            "buffer_data_size": 0,
            "buffer_offsets": [
                {
                    "buffer_name": "serving_default_input_50_output_array",
                    "offset": 2928,
                    "size": 7120
                },
                {
                    "buffer_name": "conversion_0_output_array",
                    "offset": 2928,
                    "size": 7120
                },
                {
                    "buffer_name": "conv2d_2_pad_before_output_array",
                    "offset": 2848,
                    "size": 7200
                },
                {
                    "buffer_name": "conv2d_2_output_array",
                    "offset": 0,
                    "size": 2848
                },
                {
                    "buffer_name": "pool_5_output_array",
                    "offset": 2848,
                    "size": 1424
                },
                {
                    "buffer_name": "conv2d_8_pad_before_output_array",
                    "offset": 0,
                    "size": 1456
                },
                {
                    "buffer_name": "conv2d_8_output_array",
                    "offset": 5168,
                    "size": 2848
                },
                {
                    "buffer_name": "pool_11_output_array",
                    "offset": 0,
                    "size": 1408
                },
                {
                    "buffer_name": "gemm_13_output_array",
                    "offset": 4224,
                    "size": 64
                },
                {
                    "buffer_name": "gemm_14_output_array",
                    "offset": 128,
                    "size": 2
                },
                {
                    "buffer_name": "nl_15_output_array",
                    "offset": 124,
                    "size": 2
                },
                {
                    "buffer_name": "conversion_16_output_array",
                    "offset": 0,
                    "size": 2
                },
                {
                    "buffer_name": "conv2d_2_scratch0_array",
                    "offset": 10048,
                    "size": 4544
                },
                {
                    "buffer_name": "conv2d_8_scratch0_array",
                    "offset": 1456,
                    "size": 3712
                },
                {
                    "buffer_name": "gemm_13_scratch0_array",
                    "offset": 1408,
                    "size": 2816
                },
                {
                    "buffer_name": "gemm_14_scratch0_array",
                    "offset": 0,
                    "size": 128
                },
                {
                    "buffer_name": "nl_15_scratch0_array",
                    "offset": 0,
                    "size": 124
                }
            ],
            "data_alignment": 4,
            "pool_id": 0,
            "pool_size": -1,
            "used_size": 14592
        }
    },
    "activations_alignment": 4,
    "arguments": "validate --target stm32u5 --name network -m C:/Users/Sundrax/Desktop/ModelCreating/URBAN_SHOOTING_V01_integer.tflite --compression lossless --verbosity 1 --allocate-inputs --allocate-outputs --workspace C:/Users/Sundrax/AppData/Local/Temp/mxAI_workspace10415215012302008209879872654974520 --output C:/Users/Sundrax/.stm32cubemx/network_output --valoutput C:/Users/Sundrax/Desktop/ModelCreating/test_labels.npy --valinput C:/Users/Sundrax/Desktop/ModelCreating/test.npy",
    "c_activations_count": 1,
    "c_arrays": [
        {
            "c_bits": 32,
            "c_id": 0,
            "c_mem_pool": "weights",
            "c_size_in_byte": 64,
            "c_type": "const s32",
            "format": "s32",
            "is_const": true,
            "mem_pool": "weights",
            "n_items": 16,
            "name": "conv2d_2_bias_array",
            "offset": 1920,
            "scale": [],
            "size": 16,
            "tensors": [
                {
                    "name": "conv2d_2_bias",
                    "shape": [
                        16
                    ]
                }
            ],
            "zeropoint": [],
            "zeros": 0
        },
        {
            "c_bits": 8,
            "c_id": 1,
            "c_mem_pool": "**default**",
            "c_size_in_byte": 2848,
            "c_type": "s8",
            "format": "s8",
            "is_const": false,
            "mem_pool": "activations",
            "n_items": 2848,
            "name": "conv2d_2_output_array",
            "offset": 0,
            "scale": [
                1.8273710012435913
            ],
            "size": 2848,
            "tensors": [
                {
                    "name": "conv2d_2_output",
                    "shape": [
                        1,
                        178,
                        16
                    ]
                }
            ],
            "zeropoint": [
                -128
            ]
        },
        {
            "c_bits": 8,
            "c_id": 2,
            "c_mem_pool": "**default**",
            "c_size_in_byte": 7200,
            "c_type": "s8",
            "format": "s8",
            "is_const": false,
            "mem_pool": "activations",
            "n_items": 7200,
            "name": "conv2d_2_pad_before_output_array",
            "offset": 2848,
            "scale": [
                9.579526901245117
            ],
            "size": 7200,
            "tensors": [
                {
                    "name": "conv2d_2_pad_before_output",
                    "shape": [
                        1,
                        180,
                        40
                    ]
                }
            ],
            "zeropoint": [
                95
            ]
        },
        {
            "c_bits": 8,
            "c_id": 3,
            "c_mem_pool": "**default**",
            "c_size_in_byte": 4544,
            "c_type": "s8",
            "format": "s8",
            "is_const": false,
            "mem_pool": "activations",
            "n_items": 4544,
            "name": "conv2d_2_scratch0_array",
            "offset": 10048,
            "scale": [],
            "size": 4544,
            "tensors": [
                {
                    "name": "conv2d_2_scratch0",
                    "shape": [
                        1,
                        1,
                        4544,
                        1
                    ]
                }
            ],
            "zeropoint": []
        },
        {
            "c_bits": 8,
            "c_id": 4,
            "c_mem_pool": "weights",
            "c_size_in_byte": 1920,
            "c_type": "const s8",
            "format": "s8",
            "is_const": true,
            "mem_pool": "weights",
            "n_items": 1920,
            "name": "conv2d_2_weights_array",
            "offset": 0,
            "scale": [
                0.0017681054305285215,
                0.0018387030577287078,
                0.0017871392192319036,
                0.0017279451712965965,
                0.0019401293247938156,
                0.0016841944307088852,
                0.0017940161051228642,
                0.0016758590936660767,
                0.001830368535593152,
                0.0022397080902010202,
                0.0018430455820634961,
                0.0018550201784819365,
                0.001738736522383988,
                0.0016700770938768983,
                0.0016321748262271285,
                0.0018601350020617247
            ],
            "size": 1920,
            "tensors": [
                {
                    "name": "conv2d_2_weights",
                    "shape": [
                        16,
                        1,
                        3,
                        40
                    ]
                }
            ],
            "zeropoint": [
                0,
                0,
                0,
                0,
                0,
                0,
                0,
                0,
                0,
                0,
                0,
                0,
                0,
                0,
                0,
                0
            ],
            "zeros": 0
        },
        {
            "c_bits": 32,
            "c_id": 5,
            "c_mem_pool": "weights",
            "c_size_in_byte": 128,
            "c_type": "const s32",
            "format": "s32",
            "is_const": true,
            "mem_pool": "weights",
            "n_items": 32,
            "name": "conv2d_8_bias_array",
            "offset": 3520,
            "scale": [],
            "size": 32,
            "tensors": [
                {
                    "name": "conv2d_8_bias",
                    "shape": [
                        32
                    ]
                }
            ],
            "zeropoint": [],
            "zeros": 0
        },
        {
            "c_bits": 8,
            "c_id": 6,
            "c_mem_pool": "**default**",
            "c_size_in_byte": 2848,
            "c_type": "s8",
            "format": "s8",
            "is_const": false,
            "mem_pool": "activations",
            "n_items": 2848,
            "name": "conv2d_8_output_array",
            "offset": 5168,
            "scale": [
                0.8489654064178467
            ],
            "size": 2848,
            "tensors": [
                {
                    "name": "conv2d_8_output",
                    "shape": [
                        1,
                        89,
                        32
                    ]
                }
            ],
            "zeropoint": [
                -128
            ]
        },
        {
            "c_bits": 8,
            "c_id": 7,
            "c_mem_pool": "**default**",
            "c_size_in_byte": 1456,
            "c_type": "s8",
            "format": "s8",
            "is_const": false,
            "mem_pool": "activations",
            "n_items": 1456,
            "name": "conv2d_8_pad_before_output_array",
            "offset": 0,
            "scale": [
                1.8273710012435913
            ],
            "size": 1456,
            "tensors": [
                {
                    "name": "conv2d_8_pad_before_output",
                    "shape": [
                        1,
                        91,
                        16
                    ]
                }
            ],
            "zeropoint": [
                -128
            ]
        },
        {
            "c_bits": 8,
            "c_id": 8,
            "c_mem_pool": "**default**",
            "c_size_in_byte": 3712,
            "c_type": "s8",
            "format": "s8",
            "is_const": false,
            "mem_pool": "activations",
            "n_items": 3712,
            "name": "conv2d_8_scratch0_array",
            "offset": 1456,
            "scale": [],
            "size": 3712,
            "tensors": [
                {
                    "name": "conv2d_8_scratch0",
                    "shape": [
                        1,
                        1,
                        3712,
                        1
                    ]
                }
            ],
            "zeropoint": []
        },
        {
            "c_bits": 8,
            "c_id": 9,
            "c_mem_pool": "weights",
            "c_size_in_byte": 1536,
            "c_type": "const s8",
            "format": "s8",
            "is_const": true,
            "mem_pool": "weights",
            "n_items": 1536,
            "name": "conv2d_8_weights_array",
            "offset": 1984,
            "scale": [
                0.0020778588950634003,
                0.0018253822345286608,
                0.002201170427724719,
                0.0017396303592249751,
                0.0019392977701500058,
                0.00191780598834157,
                0.0016909497790038586,
                0.0017410346772521734,
                0.0015209236880764365,
                0.0020971207413822412,
                0.0022478075698018074,
                0.002376887248829007,
                0.0017809022683650255,
                0.0017246587667614222,
                0.0019076470052823424,
                0.001876771217212081,
                0.001606783363968134,
                0.0018343226984143257,
                0.0021170449908822775,
                0.0020952539052814245,
                0.0016798905562609434,
                0.0019197085639461875,
                0.001655953237786889,
                0.0017631150549277663,
                0.0019532504957169294,
                0.001945221098139882,
                0.0019035754958167672,
                0.0014567814068868756,
                0.0017234612023457885,
                0.0017758290050551295,
                0.0019266135059297085,
                0.00177150615490973
            ],
            "size": 1536,
            "tensors": [
                {
                    "name": "conv2d_8_weights",
                    "shape": [
                        32,
                        1,
                        3,
                        16
                    ]
                }
            ],
            "zeropoint": [
                0,
                0,
                0,
                0,
                0,
                0,
                0,
                0,
                0,
                0,
                0,
                0,
                0,
                0,
                0,
                0,
                0,
                0,
                0,
                0,
                0,
                0,
                0,
                0,
                0,
                0,
                0,
                0,
                0,
                0,
                0,
                0
            ],
            "zeros": 0
        },
        {
            "c_bits": 8,
            "c_id": 10,
            "c_mem_pool": "**default**",
            "c_size_in_byte": 7120,
            "c_type": "s8",
            "format": "s8",
            "is_const": false,
            "mem_pool": "activations",
            "n_items": 7120,
            "name": "conversion_0_output_array",
            "offset": 2928,
            "scale": [
                9.579526901245117
            ],
            "size": 7120,
            "tensors": [
                {
                    "name": "conversion_0_output",
                    "shape": [
                        178,
                        40
                    ]
                }
            ],
            "zeropoint": [
                95
            ]
        },
        {
            "c_bits": 8,
            "c_id": 11,
            "c_mem_pool": "**default**",
            "c_size_in_byte": 2,
            "c_type": "u8",
            "format": "u8",
            "io_type": "output",
            "is_const": false,
            "mem_pool": "activations",
            "n_items": 2,
            "name": "conversion_16_output_array",
            "offset": 0,
            "scale": [
                0.00390625
            ],
            "size": 2,
            "tensors": [
                {
                    "name": "conversion_16_output",
                    "shape": [
                        2
                    ]
                }
            ],
            "zeropoint": [
                0
            ]
        },
        {
            "c_bits": 32,
            "c_id": 12,
            "c_mem_pool": "weights",
            "c_size_in_byte": 256,
            "c_type": "const s32",
            "format": "s32",
            "is_const": true,
            "mem_pool": "weights",
            "n_items": 64,
            "name": "gemm_13_bias_array",
            "offset": 93760,
            "scale": [],
            "size": 64,
            "tensors": [
                {
                    "name": "gemm_13_bias",
                    "shape": [
                        64
                    ]
                }
            ],
            "zeropoint": [],
            "zeros": 0
        },
        {
            "c_bits": 8,
            "c_id": 13,
            "c_mem_pool": "**default**",
            "c_size_in_byte": 64,
            "c_type": "s8",
            "format": "s8",
            "is_const": false,
            "mem_pool": "activations",
            "n_items": 64,
            "name": "gemm_13_output_array",
            "offset": 4224,
            "scale": [
                1.2311484813690186
            ],
            "size": 64,
            "tensors": [
                {
                    "name": "gemm_13_output",
                    "shape": [
                        64
                    ]
                }
            ],
            "zeropoint": [
                -128
            ]
        },
        {
            "c_bits": 16,
            "c_id": 14,
            "c_mem_pool": "**default**",
            "c_size_in_byte": 2816,
            "c_type": "s16",
            "format": "s16",
            "is_const": false,
            "mem_pool": "activations",
            "n_items": 1408,
            "name": "gemm_13_scratch0_array",
            "offset": 1408,
            "scale": [],
            "size": 1408,
            "tensors": [
                {
                    "name": "gemm_13_scratch0",
                    "shape": [
                        1,
                        1,
                        1408,
                        1
                    ]
                }
            ],
            "zeropoint": []
        },
        {
            "c_bits": 8,
            "c_id": 15,
            "c_mem_pool": "weights",
            "c_size_in_byte": 90112,
            "c_type": "const s8",
            "format": "s8",
            "is_const": true,
            "mem_pool": "weights",
            "n_items": 90112,
            "name": "gemm_13_weights_array",
            "offset": 3648,
            "scale": [
                0.002313279313966632
            ],
            "size": 90112,
            "tensors": [
                {
                    "name": "gemm_13_weights",
                    "shape": [
                        64,
                        1408
                    ]
                }
            ],
            "zeropoint": [
                0
            ],
            "zeros": 0
        },
        {
            "c_bits": 32,
            "c_id": 16,
            "c_mem_pool": "weights",
            "c_size_in_byte": 8,
            "c_type": "const s32",
            "format": "s32",
            "is_const": true,
            "mem_pool": "weights",
            "n_items": 2,
            "name": "gemm_14_bias_array",
            "offset": 94144,
            "scale": [],
            "size": 2,
            "tensors": [
                {
                    "name": "gemm_14_bias",
                    "shape": [
                        2
                    ]
                }
            ],
            "zeropoint": [],
            "zeros": 0
        },
        {
            "c_bits": 8,
            "c_id": 17,
            "c_mem_pool": "**default**",
            "c_size_in_byte": 2,
            "c_type": "s8",
            "format": "s8",
            "is_const": false,
            "mem_pool": "activations",
            "n_items": 2,
            "name": "gemm_14_output_array",
            "offset": 128,
            "scale": [
                0.7511647939682007
            ],
            "size": 2,
            "tensors": [
                {
                    "name": "gemm_14_output",
                    "shape": [
                        2
                    ]
                }
            ],
            "zeropoint": [
                -99
            ]
        },
        {
            "c_bits": 16,
            "c_id": 18,
            "c_mem_pool": "**default**",
            "c_size_in_byte": 128,
            "c_type": "s16",
            "format": "s16",
            "is_const": false,
            "mem_pool": "activations",
            "n_items": 64,
            "name": "gemm_14_scratch0_array",
            "offset": 0,
            "scale": [],
            "size": 64,
            "tensors": [
                {
                    "name": "gemm_14_scratch0",
                    "shape": [
                        1,
                        1,
                        64,
                        1
                    ]
                }
            ],
            "zeropoint": []
        },
        {
            "c_bits": 8,
            "c_id": 19,
            "c_mem_pool": "weights",
            "c_size_in_byte": 128,
            "c_type": "const s8",
            "format": "s8",
            "is_const": true,
            "mem_pool": "weights",
            "n_items": 128,
            "name": "gemm_14_weights_array",
            "offset": 94016,
            "scale": [
                0.002232576720416546
            ],
            "size": 128,
            "tensors": [
                {
                    "name": "gemm_14_weights",
                    "shape": [
                        2,
                        64
                    ]
                }
            ],
            "zeropoint": [
                0
            ],
            "zeros": 0
        },
        {
            "c_bits": 8,
            "c_id": 20,
            "c_mem_pool": "**default**",
            "c_size_in_byte": 2,
            "c_type": "s8",
            "format": "s8",
            "is_const": false,
            "mem_pool": "activations",
            "n_items": 2,
            "name": "nl_15_output_array",
            "offset": 124,
            "scale": [
                0.00390625
            ],
            "size": 2,
            "tensors": [
                {
                    "name": "nl_15_output",
                    "shape": [
                        2
                    ]
                }
            ],
            "zeropoint": [
                -128
            ]
        },
        {
            "c_bits": 32,
            "c_id": 21,
            "c_mem_pool": "**default**",
            "c_size_in_byte": 124,
            "c_type": "s32",
            "format": "s32",
            "is_const": false,
            "mem_pool": "activations",
            "n_items": 31,
            "name": "nl_15_scratch0_array",
            "offset": 0,
            "scale": [],
            "size": 31,
            "tensors": [
                {
                    "name": "nl_15_scratch0",
                    "shape": [
                        1,
                        1,
                        31,
                        1
                    ]
                }
            ],
            "zeropoint": []
        },
        {
            "c_bits": 8,
            "c_id": 22,
            "c_mem_pool": "**default**",
            "c_size_in_byte": 1408,
            "c_type": "s8",
            "format": "s8",
            "is_const": false,
            "mem_pool": "activations",
            "n_items": 1408,
            "name": "pool_11_output_array",
            "offset": 0,
            "scale": [
                0.8489654064178467
            ],
            "size": 1408,
            "tensors": [
                {
                    "name": "pool_11_output",
                    "shape": [
                        44,
                        1,
                        32
                    ]
                }
            ],
            "zeropoint": [
                -128
            ]
        },
        {
            "c_bits": 8,
            "c_id": 23,
            "c_mem_pool": "**default**",
            "c_size_in_byte": 1424,
            "c_type": "s8",
            "format": "s8",
            "is_const": false,
            "mem_pool": "activations",
            "n_items": 1424,
            "name": "pool_5_output_array",
            "offset": 2848,
            "scale": [
                1.8273710012435913
            ],
            "size": 1424,
            "tensors": [
                {
                    "name": "pool_5_output",
                    "shape": [
                        89,
                        1,
                        16
                    ]
                }
            ],
            "zeropoint": [
                -128
            ]
        },
        {
            "c_bits": 8,
            "c_id": 24,
            "c_mem_pool": "**default**",
            "c_size_in_byte": 7120,
            "c_type": "u8",
            "format": "u8",
            "io_type": "input",
            "is_const": false,
            "mem_pool": "activations",
            "n_items": 7120,
            "name": "serving_default_input_50_output_array",
            "offset": 2928,
            "scale": [
                9.579526901245117
            ],
            "size": 7120,
            "tensors": [
                {
                    "name": "serving_default_input_50_output",
                    "shape": [
                        178,
                        40
                    ]
                }
            ],
            "zeropoint": [
                223
            ]
        }
    ],
    "c_arrays_n": 25,
    "c_layers": [
        {
            "c_forward": [
                "node_convert_integer"
            ],
            "c_id": 0,
            "exec_time": {
                "counters": [],
                "cycles": 0,
                "cycles_by_macc": 0.0,
                "duration_ms": 0.0016605505358519613,
                "percentage": 0.4535602004747495
            },
            "is_wrapped": "",
            "layer_type": "Conversion",
            "m_id": 0,
            "macc": 14240,
            "name": "conversion_0",
            "op_by_type": {
                "smul_u8_s8": 14240
            },
            "rom": 0,
            "tensors": {
                "inputs": [
                    "serving_default_input_50_output"
                ],
                "outputs": [
                    "conversion_0_output"
                ],
                "scratchs": [],
                "weights": []
            },
            "weight_sparsity": [
                0.0,
                1,
                0
            ]
        },
        {
            "c_forward": [
                "forward_pad"
            ],
            "c_id": 1,
            "exec_time": {
                "counters": [],
                "cycles": 0,
                "cycles_by_macc": 0.0,
                "duration_ms": 0.0007924312302990124,
                "percentage": 0.21644343843619976
            },
            "is_wrapped": "",
            "layer_type": "Pad",
            "m_id": 2,
            "macc": 0,
            "name": "conv2d_2_pad_before",
            "op_by_type": {
                "smul_s8_s8": 0
            },
            "rom": 0,
            "tensors": {
                "inputs": [
                    "conversion_0_output"
                ],
                "outputs": [
                    "conv2d_2_pad_before_output"
                ],
                "scratchs": [],
                "weights": []
            },
            "weight_sparsity": [
                0.0,
                1,
                0
            ]
        },
        {
            "c_forward": [
                "forward_conv2d_deep_sssa8_ch"
            ],
            "c_id": 2,
            "exec_time": {
                "counters": [],
                "cycles": 0,
                "cycles_by_macc": 0.0,
                "duration_ms": 0.2153165216190279,
                "percentage": 58.81122109960186
            },
            "is_wrapped": "",
            "layer_type": "Conv2D",
            "m_id": 2,
            "macc": 341776,
            "name": "conv2d_2",
            "op_by_type": {
                "smul_s8_s8": 341776
            },
            "rom": 1984,
            "tensors": {
                "inputs": [
                    "conv2d_2_pad_before_output"
                ],
                "outputs": [
                    "conv2d_2_output"
                ],
                "scratchs": [
                    "conv2d_2_scratch0"
                ],
                "weights": [
                    "conv2d_2_weights",
                    "conv2d_2_bias"
                ]
            },
            "weight_sparsity": [
                0.0,
                1936,
                0
            ]
        },
        {
            "c_forward": [
                "forward_mp_integer_INT8"
            ],
            "c_id": 3,
            "exec_time": {
                "counters": [],
                "cycles": 0,
                "cycles_by_macc": 0.0,
                "duration_ms": 0.005205275559767978,
                "percentage": 1.4217609012443533
            },
            "is_wrapped": "",
            "layer_type": "Pool",
            "m_id": 5,
            "macc": 2848,
            "name": "pool_5",
            "op_by_type": {
                "smul_s8_s8": 2848
            },
            "rom": 0,
            "tensors": {
                "inputs": [
                    "conv2d_2_output"
                ],
                "outputs": [
                    "pool_5_output"
                ],
                "scratchs": [],
                "weights": []
            },
            "weight_sparsity": [
                0.0,
                1,
                0
            ]
        },
        {
            "c_forward": [
                "forward_pad"
            ],
            "c_id": 4,
            "exec_time": {
                "counters": [],
                "cycles": 0,
                "cycles_by_macc": 0.0,
                "duration_ms": 0.0005332569060622877,
                "percentage": 0.14565296508369446
            },
            "is_wrapped": "",
            "layer_type": "Pad",
            "m_id": 8,
            "macc": 0,
            "name": "conv2d_8_pad_before",
            "op_by_type": {
                "smul_s8_s8": 0
            },
            "rom": 0,
            "tensors": {
                "inputs": [
                    "pool_5_output"
                ],
                "outputs": [
                    "conv2d_8_pad_before_output"
                ],
                "scratchs": [],
                "weights": []
            },
            "weight_sparsity": [
                0.0,
                1,
                0
            ]
        },
        {
            "c_forward": [
                "forward_conv2d_deep_sssa8_ch"
            ],
            "c_id": 5,
            "exec_time": {
                "counters": [],
                "cycles": 0,
                "cycles_by_macc": 0.0,
                "duration_ms": 0.08912844339881194,
                "percentage": 24.344404932685187
            },
            "is_wrapped": "",
            "layer_type": "Conv2D",
            "m_id": 8,
            "macc": 136736,
            "name": "conv2d_8",
            "op_by_type": {
                "smul_s8_s8": 136736
            },
            "rom": 1664,
            "tensors": {
                "inputs": [
                    "conv2d_8_pad_before_output"
                ],
                "outputs": [
                    "conv2d_8_output"
                ],
                "scratchs": [
                    "conv2d_8_scratch0"
                ],
                "weights": [
                    "conv2d_8_weights",
                    "conv2d_8_bias"
                ]
            },
            "weight_sparsity": [
                0.0,
                1568,
                0
            ]
        },
        {
            "c_forward": [
                "forward_mp_integer_INT8"
            ],
            "c_id": 6,
            "exec_time": {
                "counters": [],
                "cycles": 0,
                "cycles_by_macc": 0.0,
                "duration_ms": 0.0045630736719740024,
                "percentage": 1.2463508726518444
            },
            "is_wrapped": "",
            "layer_type": "Pool",
            "m_id": 11,
            "macc": 2816,
            "name": "pool_11",
            "op_by_type": {
                "smul_s8_s8": 2816
            },
            "rom": 0,
            "tensors": {
                "inputs": [
                    "conv2d_8_output"
                ],
                "outputs": [
                    "pool_11_output"
                ],
                "scratchs": [],
                "weights": []
            },
            "weight_sparsity": [
                0.0,
                1,
                0
            ]
        },
        {
            "c_forward": [
                "forward_dense_integer_SSSA"
            ],
            "c_id": 7,
            "exec_time": {
                "counters": [],
                "cycles": 0,
                "cycles_by_macc": 0.0,
                "duration_ms": 0.046738534542056946,
                "percentage": 12.766090907263559
            },
            "is_wrapped": "",
            "layer_type": "Dense",
            "m_id": 13,
            "macc": 90176,
            "name": "gemm_13",
            "op_by_type": {
                "smul_s8_s8": 90176
            },
            "rom": 90368,
            "tensors": {
                "inputs": [
                    "pool_11_output"
                ],
                "outputs": [
                    "gemm_13_output"
                ],
                "scratchs": [
                    "gemm_13_scratch0"
                ],
                "weights": [
                    "gemm_13_weights",
                    "gemm_13_bias"
                ]
            },
            "weight_sparsity": [
                0.0,
                90176,
                0
            ]
        },
        {
            "c_forward": [
                "forward_dense_integer_SSSA"
            ],
            "c_id": 8,
            "exec_time": {
                "counters": [],
                "cycles": 0,
                "cycles_by_macc": 0.0,
                "duration_ms": 0.000739678933681416,
                "percentage": 0.20203475787345807
            },
            "is_wrapped": "",
            "layer_type": "Dense",
            "m_id": 14,
            "macc": 130,
            "name": "gemm_14",
            "op_by_type": {
                "smul_s8_s8": 130
            },
            "rom": 136,
            "tensors": {
                "inputs": [
                    "gemm_13_output"
                ],
                "outputs": [
                    "gemm_14_output"
                ],
                "scratchs": [
                    "gemm_14_scratch0"
                ],
                "weights": [
                    "gemm_14_weights",
                    "gemm_14_bias"
                ]
            },
            "weight_sparsity": [
                0.0,
                130,
                0
            ]
        },
        {
            "c_forward": [
                "forward_sm_integer"
            ],
            "c_id": 9,
            "exec_time": {
                "counters": [],
                "cycles": 0,
                "cycles_by_macc": 0.0,
                "duration_ms": 0.0009805046315913713,
                "percentage": 0.26781351586077207
            },
            "is_wrapped": "",
            "layer_type": "Nonlinearity",
            "m_id": 15,
            "macc": 30,
            "name": "nl_15",
            "op_by_type": {
                "op_s8_s8": 30
            },
            "rom": 0,
            "tensors": {
                "inputs": [
                    "gemm_14_output"
                ],
                "outputs": [
                    "nl_15_output"
                ],
                "scratchs": [
                    "nl_15_scratch0"
                ],
                "weights": []
            },
            "weight_sparsity": [
                0.0,
                1,
                0
            ]
        },
        {
            "c_forward": [
                "node_convert_integer"
            ],
            "c_id": 10,
            "exec_time": {
                "counters": [],
                "cycles": 0,
                "cycles_by_macc": 0.0,
                "duration_ms": 0.00045642204002750643,
                "percentage": 0.12466640882432345
            },
            "is_wrapped": "",
            "layer_type": "Conversion",
            "m_id": 16,
            "macc": 4,
            "name": "conversion_16",
            "op_by_type": {
                "smul_s8_u8": 4
            },
            "rom": 0,
            "tensors": {
                "inputs": [
                    "nl_15_output"
                ],
                "outputs": [
                    "conversion_16_output"
                ],
                "scratchs": [],
                "weights": []
            },
            "weight_sparsity": [
                0.0,
                1,
                0
            ]
        }
    ],
    "c_name": "network",
    "c_nodes_n": 11,
    "c_weights_count": 1,
    "c_weights_header": 0,
    "compilation_options": {
        "compression": "lossless",
        "optimization": "balanced",
        "options": [
            "allocate-inputs",
            "allocate-outputs"
        ]
    },
    "data_alignment": 4,
    "date_time": "2024-12-25T17:22:29+0300",
    "exec_time": {
        "cycles": 0,
        "cycles_by_macc": 0.0,
        "device": "AMD64, Intel64 Family 6 Model 158 Stepping 13, GenuineIntel, Windows",
        "duration_ms": 0.36611469306915234
    },
    "inputs": [
        "serving_default_input_50_output"
    ],
    "macc": 588756,
    "memory_footprint": {
        "activations": 14592,
        "io": [
            0,
            0
        ],
        "series": "generic",
        "weights": 94152
    },
    "memory_pools": [],
    "model_fmt": "sa/ua per tensor",
    "model_name": "URBAN_SHOOTING_V01_integer",
    "model_signature": "0x1b4cc6cc6fa3cd7ab9c307fa6edc38b5",
    "outputs": [
        "conversion_16_output"
    ],
    "st_ai_version": "1.0.0-19894",
    "tool_version": "1.0.0-19894",
    "type": "tflite",
    "version": "1.2",
    "weights": {
        "weights_array": {
            "buffer_data_size": 94152,
            "buffer_offsets": [
                {
                    "buffer_name": "conv2d_2_weights_array",
                    "offset": 0,
                    "size": 1920
                },
                {
                    "buffer_name": "conv2d_2_bias_array",
                    "offset": 1920,
                    "size": 64
                },
                {
                    "buffer_name": "conv2d_8_weights_array",
                    "offset": 1984,
                    "size": 1536
                },
                {
                    "buffer_name": "conv2d_8_bias_array",
                    "offset": 3520,
                    "size": 128
                },
                {
                    "buffer_name": "gemm_13_weights_array",
                    "offset": 3648,
                    "size": 90112
                },
                {
                    "buffer_name": "gemm_13_bias_array",
                    "offset": 93760,
                    "size": 256
                },
                {
                    "buffer_name": "gemm_14_weights_array",
                    "offset": 94016,
                    "size": 128
                },
                {
                    "buffer_name": "gemm_14_bias_array",
                    "offset": 94144,
                    "size": 8
                }
            ],
            "pool_size": -1,
            "used_size": 94152
        }
    }
}